egamma/__init__.py
egamma/dist.py
egamma/functions.py
egamma-1.0.2.dist-info/LICENSE
egamma-1.0.2.dist-info/METADATA
egamma-1.0.2.dist-info/WHEEL
egamma-1.0.2.dist-info/top_level.txt
egamma-1.0.2.dist-info/RECORD
