Metadata-Version: 2.1
Name: egamma
Version: 1.0.2
Summary: Implementation of the expanded gamma distribution
Home-page: https://github.com/FrodeDrevland/egamma
Author: Frode Drevland
Author-email: frode.drevland@ntnu.no
Classifier: Programming Language :: Python :: 3
Classifier: License :: OSI Approved :: MIT License
Classifier: Operating System :: OS Independent
Requires-Python: >=3.6
License-File: LICENSE
Requires-Dist: scipy
Requires-Dist: numpy
